pandas_extensions/__init__.py
pandas_extensions/string_extensions.py
pandas_extensions/utils_extensions.py
custom_pandas_extensions-0.0.2.dist-info/METADATA
custom_pandas_extensions-0.0.2.dist-info/WHEEL
custom_pandas_extensions-0.0.2.dist-info/top_level.txt
custom_pandas_extensions-0.0.2.dist-info/RECORD
