Metadata-Version: 2.1
Name: custom-pandas-extensions
Version: 0.0.2
Summary: Adds methods to pandas
Home-page: https://github.com/CangyuanLi/pandas_extensions
Author: Cangyuan Li
Author-email: everest229@gmail.com
License: MIT
Classifier: Programming Language :: Python :: 3
Classifier: License :: OSI Approved :: MIT License
Classifier: Operating System :: OS Independent
